synthetic_data_samples_generator/.DS_Store
synthetic_data_samples_generator/__init__.py
synthetic_data_samples_generator/configs/__init__.py
synthetic_data_samples_generator/configs/constants.py
synthetic_data_samples_generator/configs/mappers.py
synthetic_data_samples_generator/generator/__init__.py
synthetic_data_samples_generator/generator/engine.py
synthetic_data_samples_generator/sampling/__init__.py
synthetic_data_samples_generator/sampling/geojson.py
synthetic_data_samples_generator/sampling/ttl.py
synthetic_data_samples_generator/utils/__init__.py
synthetic_data_samples_generator/utils/avro.py
synthetic_data_samples_generator/utils/pandas.py
synthetic_data_samples_generator/utils/triples.py
synthetic_data_samples_generator-0.0.1.dist-info/WHEEL
synthetic_data_samples_generator-0.0.1.dist-info/METADATA
synthetic_data_samples_generator-0.0.1.dist-info/RECORD
