Metadata-Version: 2.1
Name: synthetic-data-samples-generator
Version: 0.0.1
Summary: Generates synthetic data samples on the fly for test cases.
Author: Joao Nisa
Author-email: joao.je.nisa@gmail.com
Requires-Python: >=3.11,<4.0
Classifier: Programming Language :: Python :: 3
Classifier: Programming Language :: Python :: 3.11
